{
    "$schema": "https://go.kicad.org/pcm/schemas/v1",
    "name": "KiCad to dokuly",
    "description": "File generator for dokuly",
    "description_full": "Generates production files such as Gerber, Drill, Schematic, and uploads them to dokuly",
    "identifier": "kicad-to-dokuly-plugin",
    "version": "1.0.0",
    "type": "plugin",
    "author": {
        "name": "Gaute Wierød Rønning",
        "contact": {
            "web": "https://github.com/Dokuly-PLM"
        }
    },
    "maintainer": {
        "name": "Gaute Wierød Rønning",
        "contact": {
            "web": "https://github.com/Dokuly-PLM"
        }
    },
    "resources": {
        "homepage": "https://github.com/Dokuly-PLM/kicad-to-dokuly-plugin"
    },
    "license": "GPL-3.0",
    "versions": [
        {
            "version": "1.0.0",
            "status": "stable",
            "kicad_version": "8.0.0",
            "download_url": "https://github.com/Dokuly-PLM/kicad-to-dokuly-plugin/archive/refs/tags/v1.0.0.zip",
            "download_sha256": "e65a6d44449f33d81cdc08749b37d4f1cca17a0fd99d454ae13447da0c63f603",
            "download_size": 26685
        }
    ]
  }
  